{"id":15881,"date":"2022-09-25T23:45:28","date_gmt":"2022-09-25T21:45:28","guid":{"rendered":"https:\/\/dulleni.clients.scitecs.com\/jobs\/sociologists\/"},"modified":"2022-09-25T23:45:28","modified_gmt":"2022-09-25T21:45:28","slug":"sociologists","status":"publish","type":"jobs","link":"https:\/\/dulleni.clients.scitecs.com\/jobs\/sociologists\/","title":{"rendered":"Sociologists"},"content":{"rendered":"<p>Study human society and social behavior by examining the groups and social institutions that people form, as well as various social, religious, political, and business organizations. May study the behavior and interaction of groups, trace their origin and<\/p>\n","protected":false},"featured_media":0,"template":"","meta":[],"career_pathway":[3,5,7],"acf":[],"_links":{"self":[{"href":"https:\/\/dulleni.clients.scitecs.com\/wp-json\/wp\/v2\/jobs\/15881"}],"collection":[{"href":"https:\/\/dulleni.clients.scitecs.com\/wp-json\/wp\/v2\/jobs"}],"about":[{"href":"https:\/\/dulleni.clients.scitecs.com\/wp-json\/wp\/v2\/types\/jobs"}],"wp:attachment":[{"href":"https:\/\/dulleni.clients.scitecs.com\/wp-json\/wp\/v2\/media?parent=15881"}],"wp:term":[{"taxonomy":"career_pathway","embeddable":true,"href":"https:\/\/dulleni.clients.scitecs.com\/wp-json\/wp\/v2\/career_pathway?post=15881"}],"curies":[{"name":"wp","href":"https:\/\/api.w.org\/{rel}","templated":true}]}}