{"id":16015,"date":"2022-09-25T23:45:47","date_gmt":"2022-09-25T21:45:47","guid":{"rendered":"https:\/\/dulleni.clients.scitecs.com\/jobs\/broadcast-technicians\/"},"modified":"2022-09-25T23:45:47","modified_gmt":"2022-09-25T21:45:47","slug":"broadcast-technicians","status":"publish","type":"jobs","link":"https:\/\/dulleni.clients.scitecs.com\/jobs\/broadcast-technicians\/","title":{"rendered":"Broadcast Technicians"},"content":{"rendered":"<p>Set up, operate, and maintain the electronic equipment used to acquire, edit, and transmit audio and video for radio or television programs. Control and adjust incoming and outgoing broadcast signals to regulate sound volume, signal strength, and signal cl<\/p>\n","protected":false},"featured_media":0,"template":"","meta":[],"career_pathway":[6,5,8],"acf":[],"_links":{"self":[{"href":"https:\/\/dulleni.clients.scitecs.com\/wp-json\/wp\/v2\/jobs\/16015"}],"collection":[{"href":"https:\/\/dulleni.clients.scitecs.com\/wp-json\/wp\/v2\/jobs"}],"about":[{"href":"https:\/\/dulleni.clients.scitecs.com\/wp-json\/wp\/v2\/types\/jobs"}],"wp:attachment":[{"href":"https:\/\/dulleni.clients.scitecs.com\/wp-json\/wp\/v2\/media?parent=16015"}],"wp:term":[{"taxonomy":"career_pathway","embeddable":true,"href":"https:\/\/dulleni.clients.scitecs.com\/wp-json\/wp\/v2\/career_pathway?post=16015"}],"curies":[{"name":"wp","href":"https:\/\/api.w.org\/{rel}","templated":true}]}}