{"id":16118,"date":"2022-09-25T23:46:06","date_gmt":"2022-09-25T21:46:06","guid":{"rendered":"https:\/\/dulleni.clients.scitecs.com\/jobs\/first-line-supervisors-of-police-and-detectives\/"},"modified":"2022-09-25T23:46:06","modified_gmt":"2022-09-25T21:46:06","slug":"first-line-supervisors-of-police-and-detectives","status":"publish","type":"jobs","link":"https:\/\/dulleni.clients.scitecs.com\/jobs\/first-line-supervisors-of-police-and-detectives\/","title":{"rendered":"First-Line Supervisors of Police and Detectives"},"content":{"rendered":"<p>Directly supervise and coordinate activities of members of police force.<\/p>\n","protected":false},"featured_media":0,"template":"","meta":[],"career_pathway":[6,4,7],"acf":[],"_links":{"self":[{"href":"https:\/\/dulleni.clients.scitecs.com\/wp-json\/wp\/v2\/jobs\/16118"}],"collection":[{"href":"https:\/\/dulleni.clients.scitecs.com\/wp-json\/wp\/v2\/jobs"}],"about":[{"href":"https:\/\/dulleni.clients.scitecs.com\/wp-json\/wp\/v2\/types\/jobs"}],"wp:attachment":[{"href":"https:\/\/dulleni.clients.scitecs.com\/wp-json\/wp\/v2\/media?parent=16118"}],"wp:term":[{"taxonomy":"career_pathway","embeddable":true,"href":"https:\/\/dulleni.clients.scitecs.com\/wp-json\/wp\/v2\/career_pathway?post=16118"}],"curies":[{"name":"wp","href":"https:\/\/api.w.org\/{rel}","templated":true}]}}