{"id":16210,"date":"2022-09-25T23:46:23","date_gmt":"2022-09-25T21:46:23","guid":{"rendered":"https:\/\/dulleni.clients.scitecs.com\/jobs\/real-estate-brokers\/"},"modified":"2022-09-25T23:46:23","modified_gmt":"2022-09-25T21:46:23","slug":"real-estate-brokers","status":"publish","type":"jobs","link":"https:\/\/dulleni.clients.scitecs.com\/jobs\/real-estate-brokers\/","title":{"rendered":"Real Estate Brokers"},"content":{"rendered":"<p>Operate real estate office, or work for commercial real estate firm, overseeing real estate transactions. Other duties usually include selling real estate or renting properties and arranging loans.<\/p>\n","protected":false},"featured_media":0,"template":"","meta":[],"career_pathway":[6,4],"acf":[],"_links":{"self":[{"href":"https:\/\/dulleni.clients.scitecs.com\/wp-json\/wp\/v2\/jobs\/16210"}],"collection":[{"href":"https:\/\/dulleni.clients.scitecs.com\/wp-json\/wp\/v2\/jobs"}],"about":[{"href":"https:\/\/dulleni.clients.scitecs.com\/wp-json\/wp\/v2\/types\/jobs"}],"wp:attachment":[{"href":"https:\/\/dulleni.clients.scitecs.com\/wp-json\/wp\/v2\/media?parent=16210"}],"wp:term":[{"taxonomy":"career_pathway","embeddable":true,"href":"https:\/\/dulleni.clients.scitecs.com\/wp-json\/wp\/v2\/career_pathway?post=16210"}],"curies":[{"name":"wp","href":"https:\/\/api.w.org\/{rel}","templated":true}]}}