{"id":16253,"date":"2022-09-25T23:46:28","date_gmt":"2022-09-25T21:46:28","guid":{"rendered":"https:\/\/dulleni.clients.scitecs.com\/jobs\/executive-secretaries-and-executive-administrative-assistants\/"},"modified":"2022-09-25T23:46:28","modified_gmt":"2022-09-25T21:46:28","slug":"executive-secretaries-and-executive-administrative-assistants","status":"publish","type":"jobs","link":"https:\/\/dulleni.clients.scitecs.com\/jobs\/executive-secretaries-and-executive-administrative-assistants\/","title":{"rendered":"Executive Secretaries and Executive Administrative Assistants"},"content":{"rendered":"<p>Provide high-level administrative support by conducting research, preparing statistical reports, and handling information requests, as well as performing routine administrative functions such as preparing correspondence, receiving visitors, arranging confe<\/p>\n","protected":false},"featured_media":0,"template":"","meta":[],"career_pathway":[6,4],"acf":[],"_links":{"self":[{"href":"https:\/\/dulleni.clients.scitecs.com\/wp-json\/wp\/v2\/jobs\/16253"}],"collection":[{"href":"https:\/\/dulleni.clients.scitecs.com\/wp-json\/wp\/v2\/jobs"}],"about":[{"href":"https:\/\/dulleni.clients.scitecs.com\/wp-json\/wp\/v2\/types\/jobs"}],"wp:attachment":[{"href":"https:\/\/dulleni.clients.scitecs.com\/wp-json\/wp\/v2\/media?parent=16253"}],"wp:term":[{"taxonomy":"career_pathway","embeddable":true,"href":"https:\/\/dulleni.clients.scitecs.com\/wp-json\/wp\/v2\/career_pathway?post=16253"}],"curies":[{"name":"wp","href":"https:\/\/api.w.org\/{rel}","templated":true}]}}