{"id":16347,"date":"2022-09-25T23:46:40","date_gmt":"2022-09-25T21:46:40","guid":{"rendered":"https:\/\/dulleni.clients.scitecs.com\/jobs\/electrical-and-electronics-repairers-powerhouse-substation-and-relay\/"},"modified":"2022-09-25T23:46:40","modified_gmt":"2022-09-25T21:46:40","slug":"electrical-and-electronics-repairers-powerhouse-substation-and-relay","status":"publish","type":"jobs","link":"https:\/\/dulleni.clients.scitecs.com\/jobs\/electrical-and-electronics-repairers-powerhouse-substation-and-relay\/","title":{"rendered":"Electrical and Electronics Repairers, Powerhouse, Substation, and Relay"},"content":{"rendered":"<p>Inspect, test, repair, or maintain electrical equipment in generating stations, substations, and in-service relays.<\/p>\n","protected":false},"featured_media":0,"template":"","meta":[],"career_pathway":[6,8],"acf":[],"_links":{"self":[{"href":"https:\/\/dulleni.clients.scitecs.com\/wp-json\/wp\/v2\/jobs\/16347"}],"collection":[{"href":"https:\/\/dulleni.clients.scitecs.com\/wp-json\/wp\/v2\/jobs"}],"about":[{"href":"https:\/\/dulleni.clients.scitecs.com\/wp-json\/wp\/v2\/types\/jobs"}],"wp:attachment":[{"href":"https:\/\/dulleni.clients.scitecs.com\/wp-json\/wp\/v2\/media?parent=16347"}],"wp:term":[{"taxonomy":"career_pathway","embeddable":true,"href":"https:\/\/dulleni.clients.scitecs.com\/wp-json\/wp\/v2\/career_pathway?post=16347"}],"curies":[{"name":"wp","href":"https:\/\/api.w.org\/{rel}","templated":true}]}}