{"id":16441,"date":"2022-09-25T23:46:55","date_gmt":"2022-09-25T21:46:55","guid":{"rendered":"https:\/\/dulleni.clients.scitecs.com\/jobs\/textile-knitting-and-weaving-machine-setters-operators-and-tenders\/"},"modified":"2022-09-25T23:46:55","modified_gmt":"2022-09-25T21:46:55","slug":"textile-knitting-and-weaving-machine-setters-operators-and-tenders","status":"publish","type":"jobs","link":"https:\/\/dulleni.clients.scitecs.com\/jobs\/textile-knitting-and-weaving-machine-setters-operators-and-tenders\/","title":{"rendered":"Textile Knitting and Weaving Machine Setters, Operators, and Tenders"},"content":{"rendered":"<p>Set up, operate, or tend machines that knit, loop, weave, or draw in textiles.<\/p>\n","protected":false},"featured_media":0,"template":"","meta":[],"career_pathway":[6,8],"acf":[],"_links":{"self":[{"href":"https:\/\/dulleni.clients.scitecs.com\/wp-json\/wp\/v2\/jobs\/16441"}],"collection":[{"href":"https:\/\/dulleni.clients.scitecs.com\/wp-json\/wp\/v2\/jobs"}],"about":[{"href":"https:\/\/dulleni.clients.scitecs.com\/wp-json\/wp\/v2\/types\/jobs"}],"wp:attachment":[{"href":"https:\/\/dulleni.clients.scitecs.com\/wp-json\/wp\/v2\/media?parent=16441"}],"wp:term":[{"taxonomy":"career_pathway","embeddable":true,"href":"https:\/\/dulleni.clients.scitecs.com\/wp-json\/wp\/v2\/career_pathway?post=16441"}],"curies":[{"name":"wp","href":"https:\/\/api.w.org\/{rel}","templated":true}]}}