{"id":15771,"date":"2022-09-25T23:45:14","date_gmt":"2022-09-25T21:45:14","guid":{"rendered":"https:\/\/dulleni.clients.scitecs.com\/jobs\/database-administrators\/"},"modified":"2022-09-25T23:45:14","modified_gmt":"2022-09-25T21:45:14","slug":"database-administrators","status":"publish","type":"jobs","link":"https:\/\/dulleni.clients.scitecs.com\/jobs\/database-administrators\/","title":{"rendered":"Database Administrators"},"content":{"rendered":"<p>Administer, test, and implement computer databases, applying knowledge of database management systems. Coordinate changes to computer databases. Identify, investigate, and resolve database performance issues, database capacity, and database scalability. Ma<\/p>\n","protected":false},"featured_media":0,"template":"","meta":[],"career_pathway":[6,5],"acf":[],"_links":{"self":[{"href":"https:\/\/dulleni.clients.scitecs.com\/wp-json\/wp\/v2\/jobs\/15771"}],"collection":[{"href":"https:\/\/dulleni.clients.scitecs.com\/wp-json\/wp\/v2\/jobs"}],"about":[{"href":"https:\/\/dulleni.clients.scitecs.com\/wp-json\/wp\/v2\/types\/jobs"}],"wp:attachment":[{"href":"https:\/\/dulleni.clients.scitecs.com\/wp-json\/wp\/v2\/media?parent=15771"}],"wp:term":[{"taxonomy":"career_pathway","embeddable":true,"href":"https:\/\/dulleni.clients.scitecs.com\/wp-json\/wp\/v2\/career_pathway?post=15771"}],"curies":[{"name":"wp","href":"https:\/\/api.w.org\/{rel}","templated":true}]}}