{"id":15847,"date":"2022-09-25T23:45:23","date_gmt":"2022-09-25T21:45:23","guid":{"rendered":"https:\/\/dulleni.clients.scitecs.com\/jobs\/animal-scientists\/"},"modified":"2022-09-25T23:45:23","modified_gmt":"2022-09-25T21:45:23","slug":"animal-scientists","status":"publish","type":"jobs","link":"https:\/\/dulleni.clients.scitecs.com\/jobs\/animal-scientists\/","title":{"rendered":"Animal Scientists"},"content":{"rendered":"<p>Conduct research in the genetics, nutrition, reproduction, growth, and development of domestic farm animals.<\/p>\n","protected":false},"featured_media":0,"template":"","meta":[],"career_pathway":[5,8],"acf":[],"_links":{"self":[{"href":"https:\/\/dulleni.clients.scitecs.com\/wp-json\/wp\/v2\/jobs\/15847"}],"collection":[{"href":"https:\/\/dulleni.clients.scitecs.com\/wp-json\/wp\/v2\/jobs"}],"about":[{"href":"https:\/\/dulleni.clients.scitecs.com\/wp-json\/wp\/v2\/types\/jobs"}],"wp:attachment":[{"href":"https:\/\/dulleni.clients.scitecs.com\/wp-json\/wp\/v2\/media?parent=15847"}],"wp:term":[{"taxonomy":"career_pathway","embeddable":true,"href":"https:\/\/dulleni.clients.scitecs.com\/wp-json\/wp\/v2\/career_pathway?post=15847"}],"curies":[{"name":"wp","href":"https:\/\/api.w.org\/{rel}","templated":true}]}}