{"id":15886,"date":"2022-09-25T23:45:28","date_gmt":"2022-09-25T21:45:28","guid":{"rendered":"https:\/\/dulleni.clients.scitecs.com\/jobs\/political-scientists\/"},"modified":"2022-09-25T23:45:28","modified_gmt":"2022-09-25T21:45:28","slug":"political-scientists","status":"publish","type":"jobs","link":"https:\/\/dulleni.clients.scitecs.com\/jobs\/political-scientists\/","title":{"rendered":"Political Scientists"},"content":{"rendered":"<p>Study the origin, development, and operation of political systems. May study topics, such as public opinion, political decisionmaking, and ideology. May analyze the structure and operation of governments, as well as various political entities. May conduct<\/p>\n","protected":false},"featured_media":0,"template":"","meta":[],"career_pathway":[3,5,7],"acf":[],"_links":{"self":[{"href":"https:\/\/dulleni.clients.scitecs.com\/wp-json\/wp\/v2\/jobs\/15886"}],"collection":[{"href":"https:\/\/dulleni.clients.scitecs.com\/wp-json\/wp\/v2\/jobs"}],"about":[{"href":"https:\/\/dulleni.clients.scitecs.com\/wp-json\/wp\/v2\/types\/jobs"}],"wp:attachment":[{"href":"https:\/\/dulleni.clients.scitecs.com\/wp-json\/wp\/v2\/media?parent=15886"}],"wp:term":[{"taxonomy":"career_pathway","embeddable":true,"href":"https:\/\/dulleni.clients.scitecs.com\/wp-json\/wp\/v2\/career_pathway?post=15886"}],"curies":[{"name":"wp","href":"https:\/\/api.w.org\/{rel}","templated":true}]}}