{"id":16415,"date":"2022-09-25T23:46:51","date_gmt":"2022-09-25T21:46:51","guid":{"rendered":"https:\/\/dulleni.clients.scitecs.com\/jobs\/metal-refining-furnace-operators-and-tenders\/"},"modified":"2022-09-25T23:46:51","modified_gmt":"2022-09-25T21:46:51","slug":"metal-refining-furnace-operators-and-tenders","status":"publish","type":"jobs","link":"https:\/\/dulleni.clients.scitecs.com\/jobs\/metal-refining-furnace-operators-and-tenders\/","title":{"rendered":"Metal-Refining Furnace Operators and Tenders"},"content":{"rendered":"<p>Operate or tend furnaces, such as gas, oil, coal, electric-arc or electric induction, open-hearth, or oxygen furnaces, to melt and refine metal before casting or to produce specified types of steel.<\/p>\n","protected":false},"featured_media":0,"template":"","meta":[],"career_pathway":[6,5,8],"acf":[],"_links":{"self":[{"href":"https:\/\/dulleni.clients.scitecs.com\/wp-json\/wp\/v2\/jobs\/16415"}],"collection":[{"href":"https:\/\/dulleni.clients.scitecs.com\/wp-json\/wp\/v2\/jobs"}],"about":[{"href":"https:\/\/dulleni.clients.scitecs.com\/wp-json\/wp\/v2\/types\/jobs"}],"wp:attachment":[{"href":"https:\/\/dulleni.clients.scitecs.com\/wp-json\/wp\/v2\/media?parent=16415"}],"wp:term":[{"taxonomy":"career_pathway","embeddable":true,"href":"https:\/\/dulleni.clients.scitecs.com\/wp-json\/wp\/v2\/career_pathway?post=16415"}],"curies":[{"name":"wp","href":"https:\/\/api.w.org\/{rel}","templated":true}]}}