{"id":16444,"date":"2022-09-25T23:46:55","date_gmt":"2022-09-25T21:46:55","guid":{"rendered":"https:\/\/dulleni.clients.scitecs.com\/jobs\/fabric-and-apparel-patternmakers\/"},"modified":"2022-09-25T23:46:55","modified_gmt":"2022-09-25T21:46:55","slug":"fabric-and-apparel-patternmakers","status":"publish","type":"jobs","link":"https:\/\/dulleni.clients.scitecs.com\/jobs\/fabric-and-apparel-patternmakers\/","title":{"rendered":"Fabric and Apparel Patternmakers"},"content":{"rendered":"<p>Draw and construct sets of precision master fabric patterns or layouts. May also mark and cut fabrics and apparel.<\/p>\n","protected":false},"featured_media":0,"template":"","meta":[],"career_pathway":[3,6,8],"acf":[],"_links":{"self":[{"href":"https:\/\/dulleni.clients.scitecs.com\/wp-json\/wp\/v2\/jobs\/16444"}],"collection":[{"href":"https:\/\/dulleni.clients.scitecs.com\/wp-json\/wp\/v2\/jobs"}],"about":[{"href":"https:\/\/dulleni.clients.scitecs.com\/wp-json\/wp\/v2\/types\/jobs"}],"wp:attachment":[{"href":"https:\/\/dulleni.clients.scitecs.com\/wp-json\/wp\/v2\/media?parent=16444"}],"wp:term":[{"taxonomy":"career_pathway","embeddable":true,"href":"https:\/\/dulleni.clients.scitecs.com\/wp-json\/wp\/v2\/career_pathway?post=16444"}],"curies":[{"name":"wp","href":"https:\/\/api.w.org\/{rel}","templated":true}]}}